{"regionId":7578,"absX":1856,"absY":9856,"groundFlags":[{"level":1,"x":0,"y":31,"flag":8},{"level":1,"x":0,"y":32,"flag":8},{"level":1,"x":0,"y":33,"flag":8},{"level":1,"x":0,"y":34,"flag":8},{"level":1,"x":0,"y":35,"flag":8},{"level":1,"x":0,"y":36,"flag":8},{"level":1,"x":0,"y":37,"flag":8},{"level":1,"x":0,"y":38,"flag":8},{"level":1,"x":0,"y":39,"flag":8},{"level":1,"x":0,"y":40,"flag":8},{"level":1,"x":0,"y":41,"flag":8},{"level":1,"x":0,"y":42,"flag":8},{"level":1,"x":0,"y":43,"flag":8},{"level":1,"x":0,"y":44,"flag":8},{"level":1,"x":0,"y":45,"flag":8},{"level":1,"x":0,"y":46,"flag":8},{"level":1,"x":0,"y":47,"flag":8},{"level":1,"x":0,"y":48,"flag":8},{"level":1,"x":0,"y":49,"flag":8},{"level":1,"x":0,"y":50,"flag":8},{"level":1,"x":0,"y":51,"flag":8},{"level":1,"x":0,"y":52,"flag":8},{"level":1,"x":0,"y":53,"flag":8},{"level":1,"x":0,"y":54,"flag":8},{"level":1,"x":0,"y":55,"flag":8},{"level":1,"x":0,"y":56,"flag":8},{"level":1,"x":0,"y":57,"flag":8},{"level":1,"x":0,"y":58,"flag":8},{"level":1,"x":0,"y":59,"flag":8},{"level":1,"x":0,"y":60,"flag":8},{"level":1,"x":1,"y":32,"flag":8},{"level":1,"x":1,"y":33,"flag":8},{"level":1,"x":1,"y":34,"flag":8},{"level":1,"x":1,"y":35,"flag":8},{"level":1,"x":1,"y":36,"flag":8},{"level":1,"x":1,"y":37,"flag":8},{"level":1,"x":1,"y":38,"flag":8},{"level":1,"x":1,"y":39,"flag":8},{"level":1,"x":1,"y":40,"flag":8},{"level":1,"x":1,"y":41,"flag":8},{"level":1,"x":1,"y":42,"flag":8},{"level":1,"x":1,"y":43,"flag":8},{"level":1,"x":1,"y":44,"flag":8},{"level":1,"x":1,"y":45,"flag":8},{"level":1,"x":1,"y":46,"flag":8},{"level":1,"x":1,"y":47,"flag":8},{"level":1,"x":1,"y":48,"flag":8},{"level":1,"x":1,"y":49,"flag":8},{"level":1,"x":1,"y":50,"flag":8},{"level":1,"x":1,"y":51,"flag":8},{"level":1,"x":1,"y":52,"flag":8},{"level":1,"x":1,"y":53,"flag":8},{"level":1,"x":1,"y":54,"flag":8},{"level":1,"x":1,"y":55,"flag":8},{"level":1,"x":1,"y":56,"flag":8},{"level":1,"x":1,"y":57,"flag":8},{"level":1,"x":1,"y":58,"flag":8},{"level":1,"x":1,"y":59,"flag":8},{"level":1,"x":1,"y":62,"flag":8},{"level":1,"x":1,"y":63,"flag":8},{"level":1,"x":2,"y":37,"flag":8},{"level":1,"x":2,"y":38,"flag":8},{"level":1,"x":2,"y":39,"flag":8},{"level":1,"x":2,"y":40,"flag":8},{"level":1,"x":2,"y":41,"flag":8},{"level":1,"x":2,"y":42,"flag":8},{"level":1,"x":2,"y":43,"flag":8},{"level":1,"x":2,"y":44,"flag":8},{"level":1,"x":2,"y":45,"flag":8},{"level":1,"x":2,"y":46,"flag":8},{"level":1,"x":2,"y":47,"flag":8},{"level":1,"x":2,"y":48,"flag":8},{"level":1,"x":2,"y":49,"flag":8},{"level":1,"x":2,"y":50,"flag":8},{"level":1,"x":2,"y":51,"flag":8},{"level":1,"x":2,"y":52,"flag":8},{"level":1,"x":2,"y":53,"flag":8},{"level":1,"x":2,"y":54,"flag":8},{"level":1,"x":2,"y":55,"flag":8},{"level":1,"x":2,"y":56,"flag":8},{"level":1,"x":2,"y":57,"flag":8},{"level":1,"x":2,"y":58,"flag":8},{"level":1,"x":2,"y":59,"flag":8},{"level":1,"x":2,"y":60,"flag":8},{"level":1,"x":2,"y":61,"flag":8},{"level":1,"x":2,"y":62,"flag":8},{"level":1,"x":2,"y":63,"flag":8},{"level":1,"x":3,"y":34,"flag":8},{"level":1,"x":3,"y":35,"flag":8},{"level":1,"x":3,"y":36,"flag":8},{"level":1,"x":3,"y":37,"flag":8},{"level":1,"x":3,"y":38,"flag":8},{"level":1,"x":3,"y":39,"flag":8},{"level":1,"x":3,"y":40,"flag":8},{"level":1,"x":3,"y":41,"flag":8},{"level":1,"x":3,"y":42,"flag":8},{"level":1,"x":3,"y":43,"flag":8},{"level":1,"x":3,"y":44,"flag":8},{"level":1,"x":3,"y":45,"flag":8},{"level":1,"x":3,"y":46,"flag":8},{"level":1,"x":3,"y":47,"flag":8},{"level":1,"x":3,"y":48,"flag":8},{"level":1,"x":3,"y":49,"flag":8},{"level":1,"x":3,"y":50,"flag":8},{"level":1,"x":3,"y":51,"flag":8},{"level":1,"x":3,"y":52,"flag":8},{"level":1,"x":3,"y":53,"flag":8},{"level":1,"x":3,"y":54,"flag":8},{"level":1,"x":3,"y":55,"flag":8},{"level":1,"x":3,"y":56,"flag":8},{"level":1,"x":3,"y":57,"flag":8},{"level":1,"x":3,"y":58,"flag":8},{"level":1,"x":3,"y":59,"flag":8},{"level":1,"x":3,"y":60,"flag":8},{"level":1,"x":3,"y":61,"flag":8},{"level":1,"x":3,"y":62,"flag":8},{"level":1,"x":3,"y":63,"flag":8},{"level":1,"x":4,"y":32,"flag":8},{"level":1,"x":4,"y":33,"flag":8},{"level":1,"x":4,"y":34,"flag":8},{"level":1,"x":4,"y":35,"flag":8},{"level":1,"x":4,"y":36,"flag":8},{"level":1,"x":4,"y":37,"flag":8},{"level":1,"x":4,"y":38,"flag":8},{"level":1,"x":4,"y":39,"flag":8},{"level":1,"x":4,"y":40,"flag":8},{"level":1,"x":4,"y":41,"flag":8},{"level":1,"x":4,"y":42,"flag":8},{"level":1,"x":4,"y":43,"flag":8},{"level":1,"x":4,"y":44,"flag":8},{"level":1,"x":4,"y":45,"flag":8},{"level":1,"x":4,"y":46,"flag":8},{"level":1,"x":4,"y":47,"flag":8},{"level":1,"x":4,"y":48,"flag":8},{"level":1,"x":4,"y":49,"flag":8},{"level":1,"x":4,"y":50,"flag":8},{"level":1,"x":4,"y":51,"flag":8},{"level":1,"x":4,"y":52,"flag":8},{"level":1,"x":4,"y":53,"flag":8},{"level":1,"x":4,"y":54,"flag":8},{"level":1,"x":4,"y":55,"flag":8},{"level":1,"x":4,"y":56,"flag":8},{"level":1,"x":4,"y":57,"flag":8},{"level":1,"x":4,"y":58,"flag":8},{"level":1,"x":4,"y":59,"flag":8},{"level":1,"x":4,"y":60,"flag":8},{"level":1,"x":4,"y":61,"flag":8},{"level":1,"x":4,"y":62,"flag":8},{"level":1,"x":4,"y":63,"flag":8},{"level":1,"x":5,"y":32,"flag":8},{"level":1,"x":5,"y":33,"flag":8},{"level":1,"x":5,"y":34,"flag":8},{"level":1,"x":5,"y":35,"flag":8},{"level":1,"x":5,"y":36,"flag":8},{"level":1,"x":5,"y":37,"flag":8},{"level":1,"x":5,"y":38,"flag":8},{"level":1,"x":5,"y":39,"flag":8},{"level":1,"x":5,"y":40,"flag":8},{"level":1,"x":5,"y":41,"flag":8},{"level":1,"x":5,"y":42,"flag":8},{"level":1,"x":5,"y":43,"flag":8},{"level":1,"x":5,"y":44,"flag":8},{"level":1,"x":5,"y":45,"flag":8},{"level":1,"x":5,"y":46,"flag":8},{"level":1,"x":5,"y":47,"flag":8},{"level":1,"x":5,"y":48,"flag":8},{"level":1,"x":5,"y":49,"flag":8},{"level":1,"x":5,"y":50,"flag":8},{"level":1,"x":5,"y":51,"flag":8},{"level":1,"x":5,"y":52,"flag":8},{"level":1,"x":5,"y":53,"flag":8},{"level":1,"x":5,"y":54,"flag":8},{"level":1,"x":5,"y":55,"flag":8},{"level":1,"x":5,"y":56,"flag":8},{"level":1,"x":5,"y":57,"flag":8},{"level":1,"x":5,"y":58,"flag":8},{"level":1,"x":5,"y":59,"flag":8},{"level":1,"x":5,"y":60,"flag":8},{"level":1,"x":5,"y":61,"flag":8},{"level":1,"x":5,"y":62,"flag":8},{"level":1,"x":5,"y":63,"flag":8},{"level":1,"x":6,"y":32,"flag":8},{"level":1,"x":6,"y":33,"flag":8},{"level":1,"x":6,"y":34,"flag":8},{"level":1,"x":6,"y":35,"flag":8},{"level":1,"x":6,"y":36,"flag":8},{"level":1,"x":6,"y":37,"flag":8},{"level":1,"x":6,"y":38,"flag":8},{"level":1,"x":6,"y":39,"flag":8},{"level":1,"x":6,"y":40,"flag":8},{"level":1,"x":6,"y":41,"flag":8},{"level":1,"x":6,"y":42,"flag":8},{"level":1,"x":6,"y":43,"flag":8},{"level":1,"x":6,"y":44,"flag":8},{"level":1,"x":6,"y":45,"flag":8},{"level":1,"x":6,"y":46,"flag":8},{"level":1,"x":6,"y":47,"flag":8},{"level":1,"x":6,"y":48,"flag":8},{"level":1,"x":6,"y":49,"flag":8},{"level":1,"x":6,"y":50,"flag":8},{"level":1,"x":6,"y":51,"flag":8},{"level":1,"x":6,"y":52,"flag":8},{"level":1,"x":6,"y":53,"flag":8},{"level":1,"x":6,"y":54,"flag":8},{"level":1,"x":6,"y":55,"flag":8},{"level":1,"x":6,"y":56,"flag":8},{"level":1,"x":6,"y":57,"flag":8},{"level":1,"x":6,"y":58,"flag":8},{"level":1,"x":6,"y":59,"flag":8},{"level":1,"x":6,"y":60,"flag":8},{"level":1,"x":6,"y":61,"flag":8},{"level":1,"x":6,"y":62,"flag":8},{"level":1,"x":6,"y":63,"flag":8},{"level":1,"x":7,"y":32,"flag":8},{"level":1,"x":7,"y":33,"flag":8},{"level":1,"x":7,"y":34,"flag":8},{"level":1,"x":7,"y":35,"flag":8},{"level":1,"x":7,"y":36,"flag":8},{"level":1,"x":7,"y":37,"flag":8},{"level":1,"x":7,"y":38,"flag":8},{"level":1,"x":7,"y":39,"flag":8},{"level":1,"x":7,"y":40,"flag":8},{"level":1,"x":7,"y":41,"flag":8},{"level":1,"x":7,"y":42,"flag":8},{"level":1,"x":7,"y":43,"flag":8},{"level":1,"x":7,"y":44,"flag":8},{"level":1,"x":7,"y":45,"flag":8},{"level":1,"x":7,"y":46,"flag":8},{"level":1,"x":7,"y":47,"flag":8},{"level":1,"x":7,"y":48,"flag":8},{"level":1,"x":7,"y":49,"flag":8},{"level":1,"x":7,"y":50,"flag":8},{"level":1,"x":7,"y":51,"flag":8},{"level":1,"x":7,"y":52,"flag":8},{"level":1,"x":7,"y":53,"flag":8},{"level":1,"x":7,"y":54,"flag":8},{"level":1,"x":7,"y":55,"flag":8},{"level":1,"x":7,"y":56,"flag":8},{"level":1,"x":7,"y":57,"flag":8},{"level":1,"x":7,"y":58,"flag":8},{"level":1,"x":7,"y":59,"flag":8},{"level":1,"x":7,"y":60,"flag":8},{"level":1,"x":7,"y":61,"flag":8},{"level":1,"x":7,"y":62,"flag":8},{"level":1,"x":7,"y":63,"flag":8},{"level":1,"x":8,"y":35,"flag":8},{"level":1,"x":8,"y":36,"flag":8},{"level":1,"x":8,"y":37,"flag":8},{"level":1,"x":8,"y":38,"flag":8},{"level":1,"x":8,"y":39,"flag":8},{"level":1,"x":8,"y":40,"flag":8},{"level":1,"x":8,"y":41,"flag":8},{"level":1,"x":8,"y":42,"flag":8},{"level":1,"x":8,"y":43,"flag":8},{"level":1,"x":8,"y":44,"flag":8},{"level":1,"x":8,"y":45,"flag":8},{"level":1,"x":8,"y":46,"flag":8},{"level":1,"x":8,"y":47,"flag":8},{"level":1,"x":8,"y":48,"flag":8},{"level":1,"x":8,"y":49,"flag":8},{"level":1,"x":8,"y":50,"flag":8},{"level":1,"x":8,"y":51,"flag":8},{"level":1,"x":8,"y":52,"flag":8},{"level":1,"x":8,"y":53,"flag":8},{"level":1,"x":8,"y":54,"flag":8},{"level":1,"x":8,"y":55,"flag":8},{"level":1,"x":8,"y":56,"flag":8},{"level":1,"x":8,"y":57,"flag":8},{"level":1,"x":8,"y":58,"flag":8},{"level":1,"x":8,"y":59,"flag":8},{"level":1,"x":8,"y":60,"flag":8},{"level":1,"x":8,"y":61,"flag":8},{"level":1,"x":8,"y":62,"flag":8},{"level":1,"x":8,"y":63,"flag":8},{"level":1,"x":9,"y":37,"flag":8},{"level":1,"x":9,"y":38,"flag":8},{"level":1,"x":9,"y":39,"flag":8},{"level":1,"x":9,"y":40,"flag":8},{"level":1,"x":9,"y":41,"flag":8},{"level":1,"x":9,"y":42,"flag":8},{"level":1,"x":9,"y":43,"flag":8},{"level":1,"x":9,"y":44,"flag":8},{"level":1,"x":9,"y":45,"flag":8},{"level":1,"x":9,"y":46,"flag":8},{"level":1,"x":9,"y":47,"flag":8},{"level":1,"x":9,"y":48,"flag":8},{"level":1,"x":9,"y":49,"flag":8},{"level":1,"x":9,"y":50,"flag":8},{"level":1,"x":9,"y":51,"flag":8},{"level":1,"x":9,"y":52,"flag":8},{"level":1,"x":9,"y":53,"flag":8},{"level":1,"x":9,"y":54,"flag":8},{"level":1,"x":9,"y":55,"flag":8},{"level":1,"x":9,"y":56,"flag":8},{"level":1,"x":9,"y":57,"flag":8},{"level":1,"x":9,"y":58,"flag":8},{"level":1,"x":9,"y":59,"flag":8},{"level":1,"x":9,"y":60,"flag":8},{"level":1,"x":9,"y":61,"flag":8},{"level":1,"x":9,"y":62,"flag":8},{"level":1,"x":9,"y":63,"flag":8},{"level":1,"x":10,"y":38,"flag":8},{"level":1,"x":10,"y":39,"flag":8},{"level":1,"x":10,"y":40,"flag":8},{"level":1,"x":10,"y":41,"flag":8},{"level":1,"x":10,"y":42,"flag":8},{"level":1,"x":10,"y":43,"flag":8},{"level":1,"x":10,"y":44,"flag":8},{"level":1,"x":10,"y":45,"flag":8},{"level":1,"x":10,"y":46,"flag":8},{"level":1,"x":10,"y":47,"flag":8},{"level":1,"x":10,"y":48,"flag":8},{"level":1,"x":10,"y":49,"flag":8},{"level":1,"x":10,"y":50,"flag":8},{"level":1,"x":10,"y":51,"flag":8},{"level":1,"x":10,"y":52,"flag":8},{"level":1,"x":10,"y":53,"flag":8},{"level":1,"x":10,"y":54,"flag":8},{"level":1,"x":10,"y":55,"flag":8},{"level":1,"x":10,"y":56,"flag":8},{"level":1,"x":10,"y":57,"flag":8},{"level":1,"x":10,"y":58,"flag":8},{"level":1,"x":10,"y":59,"flag":8},{"level":1,"x":10,"y":60,"flag":8},{"level":1,"x":10,"y":61,"flag":8},{"level":1,"x":10,"y":62,"flag":8},{"level":1,"x":10,"y":63,"flag":8},{"level":2,"x":0,"y":42,"flag":8},{"level":2,"x":0,"y":43,"flag":8},{"level":2,"x":0,"y":44,"flag":8},{"level":2,"x":0,"y":45,"flag":8},{"level":2,"x":0,"y":46,"flag":8},{"level":2,"x":0,"y":47,"flag":8},{"level":2,"x":1,"y":37,"flag":8},{"level":2,"x":1,"y":38,"flag":8},{"level":2,"x":1,"y":39,"flag":8},{"level":2,"x":1,"y":40,"flag":8},{"level":2,"x":1,"y":41,"flag":8},{"level":2,"x":1,"y":42,"flag":8},{"level":2,"x":1,"y":43,"flag":8},{"level":2,"x":1,"y":44,"flag":8},{"level":2,"x":1,"y":45,"flag":8},{"level":2,"x":1,"y":46,"flag":8},{"level":2,"x":1,"y":47,"flag":8},{"level":2,"x":1,"y":48,"flag":8},{"level":2,"x":1,"y":49,"flag":8},{"level":2,"x":1,"y":50,"flag":8},{"level":2,"x":2,"y":37,"flag":8},{"level":2,"x":2,"y":38,"flag":8},{"level":2,"x":2,"y":39,"flag":8},{"level":2,"x":2,"y":40,"flag":8},{"level":2,"x":2,"y":41,"flag":8},{"level":2,"x":2,"y":42,"flag":8},{"level":2,"x":2,"y":43,"flag":8},{"level":2,"x":2,"y":44,"flag":8},{"level":2,"x":2,"y":45,"flag":8},{"level":2,"x":2,"y":46,"flag":8},{"level":2,"x":2,"y":47,"flag":8},{"level":2,"x":2,"y":48,"flag":8},{"level":2,"x":2,"y":49,"flag":8},{"level":2,"x":2,"y":50,"flag":8},{"level":2,"x":3,"y":37,"flag":8},{"level":2,"x":3,"y":38,"flag":8},{"level":2,"x":3,"y":39,"flag":8},{"level":2,"x":3,"y":40,"flag":8},{"level":2,"x":3,"y":41,"flag":8},{"level":2,"x":3,"y":42,"flag":8},{"level":2,"x":3,"y":43,"flag":8},{"level":2,"x":3,"y":44,"flag":8},{"level":2,"x":3,"y":45,"flag":8},{"level":2,"x":3,"y":46,"flag":8},{"level":2,"x":3,"y":47,"flag":8},{"level":2,"x":3,"y":48,"flag":8},{"level":2,"x":3,"y":49,"flag":8},{"level":2,"x":3,"y":50,"flag":8},{"level":2,"x":4,"y":37,"flag":8},{"level":2,"x":4,"y":38,"flag":8},{"level":2,"x":4,"y":39,"flag":8},{"level":2,"x":4,"y":40,"flag":8},{"level":2,"x":4,"y":41,"flag":8},{"level":2,"x":4,"y":42,"flag":8},{"level":2,"x":4,"y":43,"flag":8},{"level":2,"x":4,"y":44,"flag":8},{"level":2,"x":4,"y":45,"flag":8},{"level":2,"x":4,"y":46,"flag":8},{"level":2,"x":4,"y":47,"flag":8},{"level":2,"x":4,"y":48,"flag":8},{"level":2,"x":4,"y":49,"flag":8},{"level":2,"x":4,"y":50,"flag":8},{"level":2,"x":5,"y":41,"flag":8},{"level":2,"x":5,"y":42,"flag":8},{"level":2,"x":5,"y":43,"flag":8},{"level":2,"x":5,"y":44,"flag":8},{"level":2,"x":5,"y":45,"flag":8},{"level":2,"x":5,"y":46,"flag":8},{"level":2,"x":5,"y":47,"flag":8},{"level":2,"x":5,"y":48,"flag":8},{"level":2,"x":5,"y":49,"flag":8},{"level":2,"x":5,"y":50,"flag":8},{"level":2,"x":6,"y":41,"flag":8},{"level":2,"x":6,"y":42,"flag":8},{"level":2,"x":6,"y":43,"flag":8},{"level":2,"x":6,"y":44,"flag":8},{"level":2,"x":6,"y":45,"flag":8},{"level":2,"x":6,"y":46,"flag":8},{"level":2,"x":6,"y":47,"flag":8},{"level":2,"x":6,"y":48,"flag":8},{"level":2,"x":6,"y":49,"flag":8},{"level":2,"x":6,"y":50,"flag":8},{"level":2,"x":7,"y":41,"flag":8},{"level":2,"x":7,"y":42,"flag":8},{"level":2,"x":7,"y":43,"flag":8},{"level":2,"x":7,"y":44,"flag":8},{"level":2,"x":7,"y":45,"flag":8},{"level":2,"x":7,"y":46,"flag":8},{"level":2,"x":7,"y":47,"flag":8},{"level":2,"x":7,"y":48,"flag":8},{"level":2,"x":7,"y":49,"flag":8},{"level":2,"x":8,"y":41,"flag":8},{"level":2,"x":8,"y":42,"flag":8},{"level":2,"x":8,"y":43,"flag":8},{"level":2,"x":8,"y":44,"flag":8},{"level":2,"x":8,"y":45,"flag":8}],"objects":[{"id":25049,"x":0,"y":31,"level":1,"type":9,"direction":2},{"id":25049,"x":0,"y":32,"level":1,"type":1,"direction":2},{"id":25049,"x":0,"y":59,"level":1,"type":1,"direction":1},{"id":25049,"x":0,"y":60,"level":1,"type":9,"direction":1},{"id":25049,"x":1,"y":32,"level":1,"type":9,"direction":2},{"id":25049,"x":1,"y":33,"level":1,"type":0,"direction":2},{"id":25049,"x":1,"y":34,"level":1,"type":0,"direction":2},{"id":25049,"x":1,"y":35,"level":1,"type":0,"direction":2},{"id":25049,"x":1,"y":36,"level":1,"type":0,"direction":2},{"id":25049,"x":1,"y":37,"level":1,"type":0,"direction":2},{"id":25049,"x":1,"y":38,"level":1,"type":0,"direction":2},{"id":25049,"x":1,"y":39,"level":1,"type":0,"direction":2},{"id":25049,"x":1,"y":40,"level":1,"type":0,"direction":2},{"id":25049,"x":1,"y":41,"level":1,"type":0,"direction":2},{"id":25049,"x":1,"y":42,"level":1,"type":0,"direction":2},{"id":25049,"x":1,"y":43,"level":1,"type":0,"direction":2},{"id":25049,"x":1,"y":44,"level":1,"type":0,"direction":2},{"id":25049,"x":1,"y":45,"level":1,"type":0,"direction":2},{"id":25049,"x":1,"y":46,"level":1,"type":0,"direction":2},{"id":25049,"x":1,"y":47,"level":1,"type":0,"direction":2},{"id":25049,"x":1,"y":48,"level":1,"type":0,"direction":2},{"id":25049,"x":1,"y":49,"level":1,"type":0,"direction":2},{"id":25049,"x":1,"y":50,"level":1,"type":0,"direction":2},{"id":25049,"x":1,"y":51,"level":1,"type":0,"direction":2},{"id":25049,"x":1,"y":52,"level":1,"type":0,"direction":2},{"id":25049,"x":1,"y":53,"level":1,"type":0,"direction":2},{"id":25049,"x":1,"y":54,"level":1,"type":0,"direction":2},{"id":25049,"x":1,"y":55,"level":1,"type":0,"direction":2},{"id":25049,"x":1,"y":56,"level":1,"type":0,"direction":2},{"id":25049,"x":1,"y":57,"level":1,"type":0,"direction":2},{"id":25049,"x":1,"y":58,"level":1,"type":0,"direction":2},{"id":25049,"x":1,"y":59,"level":1,"type":9,"direction":1},{"id":25049,"x":1,"y":62,"level":1,"type":9,"direction":3},{"id":25049,"x":1,"y":63,"level":1,"type":0,"direction":0},{"id":25049,"x":2,"y":37,"level":1,"type":9,"direction":3},{"id":25049,"x":2,"y":38,"level":1,"type":0,"direction":0},{"id":25049,"x":2,"y":39,"level":1,"type":0,"direction":0},{"id":25049,"x":2,"y":40,"level":1,"type":0,"direction":0},{"id":25049,"x":2,"y":41,"level":1,"type":0,"direction":0},{"id":25049,"x":2,"y":42,"level":1,"type":0,"direction":0},{"id":25049,"x":2,"y":43,"level":1,"type":0,"direction":0},{"id":25049,"x":2,"y":44,"level":1,"type":0,"direction":0},{"id":25049,"x":2,"y":45,"level":1,"type":0,"direction":0},{"id":25049,"x":2,"y":46,"level":1,"type":0,"direction":0},{"id":25049,"x":2,"y":47,"level":1,"type":0,"direction":0},{"id":25049,"x":2,"y":48,"level":1,"type":0,"direction":0},{"id":25049,"x":2,"y":49,"level":1,"type":0,"direction":0},{"id":25049,"x":2,"y":50,"level":1,"type":0,"direction":0},{"id":25049,"x":2,"y":51,"level":1,"type":0,"direction":0},{"id":25049,"x":2,"y":52,"level":1,"type":0,"direction":0},{"id":25049,"x":2,"y":53,"level":1,"type":0,"direction":0},{"id":25049,"x":2,"y":54,"level":1,"type":0,"direction":0},{"id":25049,"x":2,"y":55,"level":1,"type":0,"direction":0},{"id":25049,"x":2,"y":56,"level":1,"type":0,"direction":0},{"id":25049,"x":2,"y":57,"level":1,"type":0,"direction":0},{"id":25049,"x":2,"y":58,"level":1,"type":0,"direction":0},{"id":25049,"x":2,"y":59,"level":1,"type":0,"direction":0},{"id":25049,"x":2,"y":60,"level":1,"type":0,"direction":0},{"id":25049,"x":2,"y":61,"level":1,"type":0,"direction":0},{"id":25049,"x":2,"y":62,"level":1,"type":1,"direction":3},{"id":25049,"x":3,"y":34,"level":1,"type":9,"direction":3},{"id":25049,"x":3,"y":35,"level":1,"type":0,"direction":0},{"id":25049,"x":3,"y":36,"level":1,"type":0,"direction":0},{"id":25049,"x":3,"y":37,"level":1,"type":1,"direction":3},{"id":25049,"x":4,"y":32,"level":1,"type":9,"direction":3},{"id":25049,"x":4,"y":33,"level":1,"type":0,"direction":0},{"id":25049,"x":4,"y":34,"level":1,"type":1,"direction":3},{"id":25049,"x":5,"y":32,"level":1,"type":0,"direction":3},{"id":25049,"x":6,"y":32,"level":1,"type":0,"direction":3},{"id":25049,"x":7,"y":32,"level":1,"type":9,"direction":2},{"id":25049,"x":7,"y":33,"level":1,"type":0,"direction":2},{"id":25049,"x":7,"y":34,"level":1,"type":0,"direction":2},{"id":25049,"x":7,"y":35,"level":1,"type":1,"direction":2},{"id":25049,"x":8,"y":35,"level":1,"type":9,"direction":2},{"id":25049,"x":8,"y":36,"level":1,"type":0,"direction":2},{"id":25049,"x":8,"y":37,"level":1,"type":1,"direction":2},{"id":25049,"x":9,"y":37,"level":1,"type":9,"direction":2},{"id":25049,"x":9,"y":38,"level":1,"type":1,"direction":2},{"id":25049,"x":10,"y":38,"level":1,"type":9,"direction":2},{"id":25049,"x":10,"y":39,"level":1,"type":0,"direction":2},{"id":25049,"x":10,"y":40,"level":1,"type":0,"direction":2},{"id":25049,"x":10,"y":41,"level":1,"type":0,"direction":2},{"id":25049,"x":10,"y":42,"level":1,"type":0,"direction":2},{"id":25049,"x":10,"y":43,"level":1,"type":0,"direction":2},{"id":25049,"x":10,"y":44,"level":1,"type":0,"direction":2},{"id":25049,"x":10,"y":45,"level":1,"type":0,"direction":2},{"id":25049,"x":10,"y":46,"level":1,"type":0,"direction":2},{"id":25049,"x":10,"y":47,"level":1,"type":0,"direction":2},{"id":25049,"x":10,"y":48,"level":1,"type":0,"direction":2},{"id":25049,"x":10,"y":49,"level":1,"type":0,"direction":2},{"id":25049,"x":10,"y":50,"level":1,"type":0,"direction":2},{"id":25049,"x":10,"y":51,"level":1,"type":0,"direction":2},{"id":25049,"x":10,"y":52,"level":1,"type":0,"direction":2},{"id":25049,"x":10,"y":53,"level":1,"type":0,"direction":2},{"id":25049,"x":10,"y":54,"level":1,"type":0,"direction":2},{"id":25049,"x":10,"y":55,"level":1,"type":0,"direction":2},{"id":25049,"x":10,"y":56,"level":1,"type":0,"direction":2},{"id":25049,"x":10,"y":57,"level":1,"type":0,"direction":2},{"id":25049,"x":10,"y":58,"level":1,"type":0,"direction":2},{"id":25049,"x":10,"y":59,"level":1,"type":0,"direction":2},{"id":25049,"x":10,"y":60,"level":1,"type":0,"direction":2},{"id":25049,"x":10,"y":61,"level":1,"type":0,"direction":2},{"id":25049,"x":10,"y":62,"level":1,"type":0,"direction":2},{"id":25049,"x":10,"y":63,"level":1,"type":0,"direction":2},{"id":25049,"x":0,"y":42,"level":2,"type":9,"direction":3},{"id":25049,"x":0,"y":43,"level":2,"type":0,"direction":0},{"id":25049,"x":0,"y":44,"level":2,"type":0,"direction":0},{"id":25049,"x":0,"y":45,"level":2,"type":0,"direction":0},{"id":25049,"x":0,"y":46,"level":2,"type":0,"direction":0},{"id":25049,"x":0,"y":47,"level":2,"type":9,"direction":0},{"id":25049,"x":1,"y":37,"level":2,"type":9,"direction":3},{"id":25049,"x":1,"y":38,"level":2,"type":0,"direction":0},{"id":25049,"x":1,"y":39,"level":2,"type":0,"direction":0},{"id":25049,"x":1,"y":40,"level":2,"type":0,"direction":0},{"id":25049,"x":1,"y":41,"level":2,"type":0,"direction":0},{"id":25049,"x":1,"y":42,"level":2,"type":1,"direction":3},{"id":25049,"x":1,"y":47,"level":2,"type":1,"direction":0},{"id":25049,"x":1,"y":48,"level":2,"type":0,"direction":0},{"id":25049,"x":1,"y":49,"level":2,"type":0,"direction":0},{"id":25049,"x":1,"y":50,"level":2,"type":9,"direction":0},{"id":25049,"x":2,"y":37,"level":2,"type":0,"direction":3},{"id":25049,"x":2,"y":50,"level":2,"type":0,"direction":1},{"id":25049,"x":3,"y":37,"level":2,"type":0,"direction":3},{"id":25049,"x":3,"y":50,"level":2,"type":0,"direction":1},{"id":25049,"x":4,"y":37,"level":2,"type":9,"direction":2},{"id":25049,"x":4,"y":38,"level":2,"type":0,"direction":2},{"id":25049,"x":4,"y":39,"level":2,"type":0,"direction":2},{"id":25049,"x":4,"y":40,"level":2,"type":0,"direction":2},{"id":25049,"x":4,"y":41,"level":2,"type":1,"direction":2},{"id":25049,"x":4,"y":50,"level":2,"type":0,"direction":1},{"id":25049,"x":5,"y":41,"level":2,"type":0,"direction":3},{"id":25049,"x":5,"y":50,"level":2,"type":0,"direction":1},{"id":25049,"x":6,"y":41,"level":2,"type":0,"direction":3},{"id":25049,"x":6,"y":49,"level":2,"type":1,"direction":1},{"id":25049,"x":6,"y":50,"level":2,"type":9,"direction":1},{"id":25049,"x":7,"y":41,"level":2,"type":0,"direction":3},{"id":25049,"x":7,"y":45,"level":2,"type":1,"direction":1},{"id":25049,"x":7,"y":46,"level":2,"type":0,"direction":2},{"id":25049,"x":7,"y":47,"level":2,"type":0,"direction":2},{"id":25049,"x":7,"y":48,"level":2,"type":0,"direction":2},{"id":25049,"x":7,"y":49,"level":2,"type":9,"direction":1},{"id":25049,"x":8,"y":41,"level":2,"type":9,"direction":2},{"id":25049,"x":8,"y":42,"level":2,"type":0,"direction":2},{"id":25049,"x":8,"y":43,"level":2,"type":0,"direction":2},{"id":25049,"x":8,"y":44,"level":2,"type":0,"direction":2},{"id":25049,"x":8,"y":45,"level":2,"type":9,"direction":1},{"id":25057,"x":0,"y":26,"level":0,"type":10,"direction":0},{"id":25057,"x":0,"y":27,"level":0,"type":10,"direction":0},{"id":25057,"x":0,"y":28,"level":0,"type":10,"direction":0},{"id":25057,"x":0,"y":29,"level":0,"type":10,"direction":0},{"id":25057,"x":0,"y":30,"level":0,"type":10,"direction":0},{"id":25057,"x":0,"y":31,"level":0,"type":10,"direction":0},{"id":25057,"x":0,"y":32,"level":0,"type":10,"direction":0},{"id":25057,"x":0,"y":33,"level":0,"type":10,"direction":0},{"id":25057,"x":0,"y":34,"level":0,"type":10,"direction":0},{"id":25057,"x":0,"y":35,"level":0,"type":10,"direction":0},{"id":25057,"x":0,"y":36,"level":0,"type":10,"direction":0},{"id":25057,"x":0,"y":37,"level":0,"type":10,"direction":0},{"id":25057,"x":0,"y":38,"level":0,"type":10,"direction":0},{"id":25057,"x":0,"y":39,"level":0,"type":10,"direction":0},{"id":25057,"x":0,"y":40,"level":0,"type":10,"direction":0},{"id":25057,"x":0,"y":41,"level":0,"type":10,"direction":0},{"id":25057,"x":0,"y":42,"level":0,"type":10,"direction":0},{"id":25057,"x":0,"y":43,"level":0,"type":10,"direction":0},{"id":25057,"x":0,"y":44,"level":0,"type":10,"direction":0},{"id":25057,"x":0,"y":45,"level":0,"type":10,"direction":0},{"id":25057,"x":0,"y":46,"level":0,"type":10,"direction":0},{"id":25057,"x":0,"y":47,"level":0,"type":10,"direction":0},{"id":25057,"x":0,"y":48,"level":0,"type":10,"direction":0},{"id":25057,"x":0,"y":49,"level":0,"type":10,"direction":0},{"id":25057,"x":0,"y":50,"level":0,"type":10,"direction":0},{"id":25057,"x":0,"y":51,"level":0,"type":10,"direction":0},{"id":25057,"x":0,"y":52,"level":0,"type":10,"direction":0},{"id":25057,"x":0,"y":53,"level":0,"type":10,"direction":0},{"id":25057,"x":0,"y":54,"level":0,"type":10,"direction":0},{"id":25057,"x":0,"y":55,"level":0,"type":10,"direction":0},{"id":25057,"x":0,"y":56,"level":0,"type":10,"direction":0},{"id":25057,"x":0,"y":57,"level":0,"type":10,"direction":0},{"id":25057,"x":0,"y":58,"level":0,"type":10,"direction":0},{"id":25057,"x":0,"y":59,"level":0,"type":10,"direction":0},{"id":25057,"x":0,"y":60,"level":0,"type":10,"direction":0},{"id":25057,"x":0,"y":61,"level":0,"type":10,"direction":0},{"id":25057,"x":0,"y":62,"level":0,"type":10,"direction":0},{"id":25057,"x":0,"y":63,"level":0,"type":10,"direction":0},{"id":25057,"x":1,"y":26,"level":0,"type":10,"direction":0},{"id":25057,"x":1,"y":27,"level":0,"type":10,"direction":0},{"id":25057,"x":1,"y":28,"level":0,"type":10,"direction":0},{"id":25057,"x":1,"y":29,"level":0,"type":10,"direction":0},{"id":25057,"x":1,"y":30,"level":0,"type":10,"direction":0},{"id":25057,"x":1,"y":31,"level":0,"type":10,"direction":0},{"id":25057,"x":1,"y":32,"level":0,"type":10,"direction":0},{"id":25057,"x":1,"y":33,"level":0,"type":10,"direction":0},{"id":25057,"x":1,"y":34,"level":0,"type":10,"direction":0},{"id":25057,"x":1,"y":35,"level":0,"type":10,"direction":0},{"id":25057,"x":1,"y":36,"level":0,"type":10,"direction":0},{"id":25057,"x":1,"y":37,"level":0,"type":10,"direction":0},{"id":25057,"x":1,"y":38,"level":0,"type":10,"direction":0},{"id":25057,"x":1,"y":39,"level":0,"type":10,"direction":0},{"id":25057,"x":1,"y":40,"level":0,"type":10,"direction":0},{"id":25057,"x":1,"y":41,"level":0,"type":10,"direction":0},{"id":25057,"x":1,"y":42,"level":0,"type":10,"direction":0},{"id":25057,"x":1,"y":43,"level":0,"type":10,"direction":0},{"id":25057,"x":1,"y":44,"level":0,"type":10,"direction":0},{"id":25057,"x":1,"y":45,"level":0,"type":10,"direction":0},{"id":25057,"x":1,"y":46,"level":0,"type":10,"direction":0},{"id":25057,"x":1,"y":47,"level":0,"type":10,"direction":0},{"id":25057,"x":1,"y":48,"level":0,"type":10,"direction":0},{"id":25057,"x":1,"y":49,"level":0,"type":10,"direction":0},{"id":25057,"x":1,"y":50,"level":0,"type":10,"direction":0},{"id":25057,"x":1,"y":51,"level":0,"type":10,"direction":0},{"id":25057,"x":1,"y":52,"level":0,"type":10,"direction":0},{"id":25057,"x":1,"y":53,"level":0,"type":10,"direction":0},{"id":25057,"x":1,"y":54,"level":0,"type":10,"direction":0},{"id":25057,"x":1,"y":55,"level":0,"type":10,"direction":0},{"id":25057,"x":1,"y":56,"level":0,"type":10,"direction":0},{"id":25057,"x":1,"y":57,"level":0,"type":10,"direction":0},{"id":25057,"x":1,"y":58,"level":0,"type":10,"direction":0},{"id":25057,"x":1,"y":59,"level":0,"type":10,"direction":0},{"id":25057,"x":1,"y":60,"level":0,"type":10,"direction":0},{"id":25057,"x":1,"y":61,"level":0,"type":10,"direction":0},{"id":25057,"x":1,"y":62,"level":0,"type":10,"direction":0},{"id":25057,"x":1,"y":63,"level":0,"type":10,"direction":0},{"id":25057,"x":2,"y":26,"level":0,"type":10,"direction":0},{"id":25057,"x":2,"y":27,"level":0,"type":10,"direction":0},{"id":25057,"x":2,"y":28,"level":0,"type":10,"direction":0},{"id":25057,"x":2,"y":29,"level":0,"type":10,"direction":0},{"id":25057,"x":2,"y":30,"level":0,"type":10,"direction":0},{"id":25057,"x":2,"y":31,"level":0,"type":10,"direction":0},{"id":25057,"x":2,"y":32,"level":0,"type":10,"direction":0},{"id":25057,"x":2,"y":33,"level":0,"type":10,"direction":0},{"id":25057,"x":2,"y":34,"level":0,"type":10,"direction":0},{"id":25057,"x":2,"y":35,"level":0,"type":10,"direction":0},{"id":25057,"x":2,"y":36,"level":0,"type":10,"direction":0},{"id":25057,"x":2,"y":37,"level":0,"type":10,"direction":0},{"id":25057,"x":2,"y":38,"level":0,"type":10,"direction":0},{"id":25057,"x":2,"y":39,"level":0,"type":10,"direction":0},{"id":25057,"x":2,"y":40,"level":0,"type":10,"direction":0},{"id":25057,"x":2,"y":41,"level":0,"type":10,"direction":0},{"id":25057,"x":2,"y":42,"level":0,"type":10,"direction":0},{"id":25057,"x":2,"y":43,"level":0,"type":10,"direction":0},{"id":25057,"x":2,"y":44,"level":0,"type":10,"direction":0},{"id":25057,"x":2,"y":45,"level":0,"type":10,"direction":0},{"id":25057,"x":2,"y":46,"level":0,"type":10,"direction":0},{"id":25057,"x":2,"y":47,"level":0,"type":10,"direction":0},{"id":25057,"x":2,"y":48,"level":0,"type":10,"direction":0},{"id":25057,"x":2,"y":49,"level":0,"type":10,"direction":0},{"id":25057,"x":2,"y":50,"level":0,"type":10,"direction":0},{"id":25057,"x":2,"y":51,"level":0,"type":10,"direction":0},{"id":25057,"x":2,"y":52,"level":0,"type":10,"direction":0},{"id":25057,"x":2,"y":53,"level":0,"type":10,"direction":0},{"id":25057,"x":2,"y":54,"level":0,"type":10,"direction":0},{"id":25057,"x":2,"y":55,"level":0,"type":10,"direction":0},{"id":25057,"x":2,"y":56,"level":0,"type":10,"direction":0},{"id":25057,"x":2,"y":57,"level":0,"type":10,"direction":0},{"id":25057,"x":2,"y":58,"level":0,"type":10,"direction":0},{"id":25057,"x":2,"y":59,"level":0,"type":10,"direction":0},{"id":25057,"x":2,"y":60,"level":0,"type":10,"direction":0},{"id":25057,"x":2,"y":61,"level":0,"type":10,"direction":0},{"id":25057,"x":2,"y":62,"level":0,"type":10,"direction":0},{"id":25057,"x":2,"y":63,"level":0,"type":10,"direction":0},{"id":25057,"x":3,"y":26,"level":0,"type":10,"direction":0},{"id":25057,"x":3,"y":27,"level":0,"type":10,"direction":0},{"id":25057,"x":3,"y":28,"level":0,"type":10,"direction":0},{"id":25057,"x":3,"y":29,"level":0,"type":10,"direction":0},{"id":25057,"x":3,"y":30,"level":0,"type":10,"direction":0},{"id":25057,"x":3,"y":31,"level":0,"type":10,"direction":0},{"id":25057,"x":3,"y":32,"level":0,"type":10,"direction":0},{"id":25057,"x":3,"y":33,"level":0,"type":10,"direction":0},{"id":25057,"x":3,"y":34,"level":0,"type":10,"direction":0},{"id":25057,"x":3,"y":35,"level":0,"type":10,"direction":0},{"id":25057,"x":3,"y":36,"level":0,"type":10,"direction":0},{"id":25057,"x":3,"y":37,"level":0,"type":10,"direction":0},{"id":25057,"x":3,"y":38,"level":0,"type":10,"direction":0},{"id":25057,"x":3,"y":39,"level":0,"type":10,"direction":0},{"id":25057,"x":3,"y":40,"level":0,"type":10,"direction":0},{"id":25057,"x":3,"y":41,"level":0,"type":10,"direction":0},{"id":25057,"x":3,"y":42,"level":0,"type":10,"direction":0},{"id":25057,"x":3,"y":43,"level":0,"type":10,"direction":0},{"id":25057,"x":3,"y":44,"level":0,"type":10,"direction":0},{"id":25057,"x":3,"y":45,"level":0,"type":10,"direction":0},{"id":25057,"x":3,"y":46,"level":0,"type":10,"direction":0},{"id":25057,"x":3,"y":47,"level":0,"type":10,"direction":0},{"id":25057,"x":3,"y":48,"level":0,"type":10,"direction":0},{"id":25057,"x":3,"y":49,"level":0,"type":10,"direction":0},{"id":25057,"x":3,"y":50,"level":0,"type":10,"direction":0},{"id":25057,"x":3,"y":51,"level":0,"type":10,"direction":0},{"id":25057,"x":3,"y":52,"level":0,"type":10,"direction":0},{"id":25057,"x":3,"y":53,"level":0,"type":10,"direction":0},{"id":25057,"x":3,"y":54,"level":0,"type":10,"direction":0},{"id":25057,"x":3,"y":55,"level":0,"type":10,"direction":0},{"id":25057,"x":3,"y":56,"level":0,"type":10,"direction":0},{"id":25057,"x":3,"y":57,"level":0,"type":10,"direction":0},{"id":25057,"x":3,"y":58,"level":0,"type":10,"direction":0},{"id":25057,"x":3,"y":59,"level":0,"type":10,"direction":0},{"id":25057,"x":3,"y":60,"level":0,"type":10,"direction":0},{"id":25057,"x":3,"y":61,"level":0,"type":10,"direction":0},{"id":25057,"x":3,"y":62,"level":0,"type":10,"direction":0},{"id":25057,"x":3,"y":63,"level":0,"type":10,"direction":0},{"id":25057,"x":4,"y":26,"level":0,"type":10,"direction":0},{"id":25057,"x":4,"y":27,"level":0,"type":10,"direction":0},{"id":25057,"x":4,"y":28,"level":0,"type":10,"direction":0},{"id":25057,"x":4,"y":29,"level":0,"type":10,"direction":0},{"id":25057,"x":4,"y":30,"level":0,"type":10,"direction":0},{"id":25057,"x":4,"y":31,"level":0,"type":10,"direction":0},{"id":25057,"x":4,"y":32,"level":0,"type":10,"direction":0},{"id":25057,"x":4,"y":33,"level":0,"type":10,"direction":0},{"id":25057,"x":4,"y":34,"level":0,"type":10,"direction":0},{"id":25057,"x":4,"y":35,"level":0,"type":10,"direction":0},{"id":25057,"x":4,"y":36,"level":0,"type":10,"direction":0},{"id":25057,"x":4,"y":37,"level":0,"type":10,"direction":0},{"id":25057,"x":4,"y":38,"level":0,"type":10,"direction":0},{"id":25057,"x":4,"y":39,"level":0,"type":10,"direction":0},{"id":25057,"x":4,"y":40,"level":0,"type":10,"direction":0},{"id":25057,"x":4,"y":41,"level":0,"type":10,"direction":0},{"id":25057,"x":4,"y":42,"level":0,"type":10,"direction":0},{"id":25057,"x":4,"y":43,"level":0,"type":10,"direction":0},{"id":25057,"x":4,"y":44,"level":0,"type":10,"direction":0},{"id":25057,"x":4,"y":45,"level":0,"type":10,"direction":0},{"id":25057,"x":4,"y":46,"level":0,"type":10,"direction":0},{"id":25057,"x":4,"y":47,"level":0,"type":10,"direction":0},{"id":25057,"x":4,"y":48,"level":0,"type":10,"direction":0},{"id":25057,"x":4,"y":49,"level":0,"type":10,"direction":0},{"id":25057,"x":4,"y":50,"level":0,"type":10,"direction":0},{"id":25057,"x":4,"y":51,"level":0,"type":10,"direction":0},{"id":25057,"x":4,"y":52,"level":0,"type":10,"direction":0},{"id":25057,"x":4,"y":53,"level":0,"type":10,"direction":0},{"id":25057,"x":4,"y":54,"level":0,"type":10,"direction":0},{"id":25057,"x":4,"y":55,"level":0,"type":10,"direction":0},{"id":25057,"x":4,"y":56,"level":0,"type":10,"direction":0},{"id":25057,"x":4,"y":57,"level":0,"type":10,"direction":0},{"id":25057,"x":4,"y":58,"level":0,"type":10,"direction":0},{"id":25057,"x":4,"y":59,"level":0,"type":10,"direction":0},{"id":25057,"x":4,"y":60,"level":0,"type":10,"direction":0},{"id":25057,"x":4,"y":61,"level":0,"type":10,"direction":0},{"id":25057,"x":4,"y":62,"level":0,"type":10,"direction":0},{"id":25057,"x":4,"y":63,"level":0,"type":10,"direction":0},{"id":25057,"x":5,"y":26,"level":0,"type":10,"direction":0},{"id":25057,"x":5,"y":27,"level":0,"type":10,"direction":0},{"id":25057,"x":5,"y":28,"level":0,"type":10,"direction":0},{"id":25057,"x":5,"y":29,"level":0,"type":10,"direction":0},{"id":25057,"x":5,"y":30,"level":0,"type":10,"direction":0},{"id":25057,"x":5,"y":31,"level":0,"type":10,"direction":0},{"id":25057,"x":5,"y":32,"level":0,"type":10,"direction":0},{"id":25057,"x":5,"y":33,"level":0,"type":10,"direction":0},{"id":25057,"x":5,"y":34,"level":0,"type":10,"direction":0},{"id":25057,"x":5,"y":35,"level":0,"type":10,"direction":0},{"id":25057,"x":5,"y":36,"level":0,"type":10,"direction":0},{"id":25057,"x":5,"y":37,"level":0,"type":10,"direction":0},{"id":25057,"x":5,"y":38,"level":0,"type":10,"direction":0},{"id":25057,"x":5,"y":39,"level":0,"type":10,"direction":0},{"id":25057,"x":5,"y":40,"level":0,"type":10,"direction":0},{"id":25057,"x":5,"y":41,"level":0,"type":10,"direction":0},{"id":25057,"x":5,"y":42,"level":0,"type":10,"direction":0},{"id":25057,"x":5,"y":43,"level":0,"type":10,"direction":0},{"id":25057,"x":5,"y":44,"level":0,"type":10,"direction":0},{"id":25057,"x":5,"y":45,"level":0,"type":10,"direction":0},{"id":25057,"x":5,"y":46,"level":0,"type":10,"direction":0},{"id":25057,"x":5,"y":47,"level":0,"type":10,"direction":0},{"id":25057,"x":5,"y":48,"level":0,"type":10,"direction":0},{"id":25057,"x":5,"y":49,"level":0,"type":10,"direction":0},{"id":25057,"x":5,"y":50,"level":0,"type":10,"direction":0},{"id":25057,"x":5,"y":51,"level":0,"type":10,"direction":0},{"id":25057,"x":5,"y":52,"level":0,"type":10,"direction":0},{"id":25057,"x":5,"y":53,"level":0,"type":10,"direction":0},{"id":25057,"x":5,"y":54,"level":0,"type":10,"direction":0},{"id":25057,"x":5,"y":55,"level":0,"type":10,"direction":0},{"id":25057,"x":5,"y":56,"level":0,"type":10,"direction":0},{"id":25057,"x":5,"y":57,"level":0,"type":10,"direction":0},{"id":25057,"x":5,"y":58,"level":0,"type":10,"direction":0},{"id":25057,"x":5,"y":59,"level":0,"type":10,"direction":0},{"id":25057,"x":5,"y":60,"level":0,"type":10,"direction":0},{"id":25057,"x":5,"y":61,"level":0,"type":10,"direction":0},{"id":25057,"x":5,"y":62,"level":0,"type":10,"direction":0},{"id":25057,"x":5,"y":63,"level":0,"type":10,"direction":0},{"id":25057,"x":6,"y":26,"level":0,"type":10,"direction":0},{"id":25057,"x":6,"y":27,"level":0,"type":10,"direction":0},{"id":25057,"x":6,"y":28,"level":0,"type":10,"direction":0},{"id":25057,"x":6,"y":29,"level":0,"type":10,"direction":0},{"id":25057,"x":6,"y":30,"level":0,"type":10,"direction":0},{"id":25057,"x":6,"y":31,"level":0,"type":10,"direction":0},{"id":25057,"x":6,"y":32,"level":0,"type":10,"direction":0},{"id":25057,"x":6,"y":33,"level":0,"type":10,"direction":0},{"id":25057,"x":6,"y":34,"level":0,"type":10,"direction":0},{"id":25057,"x":6,"y":35,"level":0,"type":10,"direction":0},{"id":25057,"x":6,"y":36,"level":0,"type":10,"direction":0},{"id":25057,"x":6,"y":37,"level":0,"type":10,"direction":0},{"id":25057,"x":6,"y":38,"level":0,"type":10,"direction":0},{"id":25057,"x":6,"y":39,"level":0,"type":10,"direction":0},{"id":25057,"x":6,"y":40,"level":0,"type":10,"direction":0},{"id":25057,"x":6,"y":41,"level":0,"type":10,"direction":0},{"id":25057,"x":6,"y":42,"level":0,"type":10,"direction":0},{"id":25057,"x":6,"y":43,"level":0,"type":10,"direction":0},{"id":25057,"x":6,"y":44,"level":0,"type":10,"direction":0},{"id":25057,"x":6,"y":45,"level":0,"type":10,"direction":0},{"id":25057,"x":6,"y":46,"level":0,"type":10,"direction":0},{"id":25057,"x":6,"y":47,"level":0,"type":10,"direction":0},{"id":25057,"x":6,"y":48,"level":0,"type":10,"direction":0},{"id":25057,"x":6,"y":49,"level":0,"type":10,"direction":0},{"id":25057,"x":6,"y":50,"level":0,"type":10,"direction":0},{"id":25057,"x":6,"y":51,"level":0,"type":10,"direction":0},{"id":25057,"x":6,"y":52,"level":0,"type":10,"direction":0},{"id":25057,"x":6,"y":53,"level":0,"type":10,"direction":0},{"id":25057,"x":6,"y":54,"level":0,"type":10,"direction":0},{"id":25057,"x":6,"y":55,"level":0,"type":10,"direction":0},{"id":25057,"x":6,"y":56,"level":0,"type":10,"direction":0},{"id":25057,"x":6,"y":57,"level":0,"type":10,"direction":0},{"id":25057,"x":6,"y":58,"level":0,"type":10,"direction":0},{"id":25057,"x":6,"y":59,"level":0,"type":10,"direction":0},{"id":25057,"x":6,"y":60,"level":0,"type":10,"direction":0},{"id":25057,"x":6,"y":61,"level":0,"type":10,"direction":0},{"id":25057,"x":6,"y":62,"level":0,"type":10,"direction":0},{"id":25057,"x":6,"y":63,"level":0,"type":10,"direction":0},{"id":25057,"x":7,"y":26,"level":0,"type":10,"direction":0},{"id":25057,"x":7,"y":27,"level":0,"type":10,"direction":0},{"id":25057,"x":7,"y":28,"level":0,"type":10,"direction":0},{"id":25057,"x":7,"y":29,"level":0,"type":10,"direction":0},{"id":25057,"x":7,"y":30,"level":0,"type":10,"direction":0},{"id":25057,"x":7,"y":31,"level":0,"type":10,"direction":0},{"id":25057,"x":7,"y":32,"level":0,"type":10,"direction":0},{"id":25057,"x":7,"y":33,"level":0,"type":10,"direction":0},{"id":25057,"x":7,"y":34,"level":0,"type":10,"direction":0},{"id":25057,"x":7,"y":35,"level":0,"type":10,"direction":0},{"id":25057,"x":7,"y":36,"level":0,"type":10,"direction":0},{"id":25057,"x":7,"y":37,"level":0,"type":10,"direction":0},{"id":25057,"x":7,"y":38,"level":0,"type":10,"direction":0},{"id":25057,"x":7,"y":39,"level":0,"type":10,"direction":0},{"id":25057,"x":7,"y":40,"level":0,"type":10,"direction":0},{"id":25057,"x":7,"y":41,"level":0,"type":10,"direction":0},{"id":25057,"x":7,"y":42,"level":0,"type":10,"direction":0},{"id":25057,"x":7,"y":43,"level":0,"type":10,"direction":0},{"id":25057,"x":7,"y":44,"level":0,"type":10,"direction":0},{"id":25057,"x":7,"y":45,"level":0,"type":10,"direction":0},{"id":25057,"x":7,"y":46,"level":0,"type":10,"direction":0},{"id":25057,"x":7,"y":47,"level":0,"type":10,"direction":0},{"id":25057,"x":7,"y":48,"level":0,"type":10,"direction":0},{"id":25057,"x":7,"y":49,"level":0,"type":10,"direction":0},{"id":25057,"x":7,"y":50,"level":0,"type":10,"direction":0},{"id":25057,"x":7,"y":51,"level":0,"type":10,"direction":0},{"id":25057,"x":7,"y":52,"level":0,"type":10,"direction":0},{"id":25057,"x":7,"y":53,"level":0,"type":10,"direction":0},{"id":25057,"x":7,"y":54,"level":0,"type":10,"direction":0},{"id":25057,"x":7,"y":55,"level":0,"type":10,"direction":0},{"id":25057,"x":7,"y":56,"level":0,"type":10,"direction":0},{"id":25057,"x":7,"y":57,"level":0,"type":10,"direction":0},{"id":25057,"x":7,"y":58,"level":0,"type":10,"direction":0},{"id":25057,"x":7,"y":59,"level":0,"type":10,"direction":0},{"id":25057,"x":7,"y":60,"level":0,"type":10,"direction":0},{"id":25057,"x":7,"y":61,"level":0,"type":10,"direction":0},{"id":25057,"x":7,"y":62,"level":0,"type":10,"direction":0},{"id":25057,"x":7,"y":63,"level":0,"type":10,"direction":0},{"id":25057,"x":8,"y":26,"level":0,"type":10,"direction":0},{"id":25057,"x":8,"y":27,"level":0,"type":10,"direction":0},{"id":25057,"x":8,"y":28,"level":0,"type":10,"direction":0},{"id":25057,"x":8,"y":29,"level":0,"type":10,"direction":0},{"id":25057,"x":8,"y":30,"level":0,"type":10,"direction":0},{"id":25057,"x":8,"y":31,"level":0,"type":10,"direction":0},{"id":25057,"x":8,"y":32,"level":0,"type":10,"direction":0},{"id":25057,"x":8,"y":33,"level":0,"type":10,"direction":0},{"id":25057,"x":8,"y":34,"level":0,"type":10,"direction":0},{"id":25057,"x":8,"y":35,"level":0,"type":10,"direction":0},{"id":25057,"x":8,"y":36,"level":0,"type":10,"direction":0},{"id":25057,"x":8,"y":37,"level":0,"type":10,"direction":0},{"id":25057,"x":8,"y":38,"level":0,"type":10,"direction":0},{"id":25057,"x":8,"y":39,"level":0,"type":10,"direction":0},{"id":25057,"x":8,"y":40,"level":0,"type":10,"direction":0},{"id":25057,"x":8,"y":41,"level":0,"type":10,"direction":0},{"id":25057,"x":8,"y":42,"level":0,"type":10,"direction":0},{"id":25057,"x":8,"y":43,"level":0,"type":10,"direction":0},{"id":25057,"x":8,"y":44,"level":0,"type":10,"direction":0},{"id":25057,"x":8,"y":45,"level":0,"type":10,"direction":0},{"id":25057,"x":8,"y":46,"level":0,"type":10,"direction":0},{"id":25057,"x":8,"y":47,"level":0,"type":10,"direction":0},{"id":25057,"x":8,"y":48,"level":0,"type":10,"direction":0},{"id":25057,"x":8,"y":49,"level":0,"type":10,"direction":0},{"id":25057,"x":8,"y":50,"level":0,"type":10,"direction":0},{"id":25057,"x":8,"y":51,"level":0,"type":10,"direction":0},{"id":25057,"x":8,"y":52,"level":0,"type":10,"direction":0},{"id":25057,"x":8,"y":53,"level":0,"type":10,"direction":0},{"id":25057,"x":8,"y":54,"level":0,"type":10,"direction":0},{"id":25057,"x":8,"y":55,"level":0,"type":10,"direction":0},{"id":25057,"x":8,"y":56,"level":0,"type":10,"direction":0},{"id":25057,"x":8,"y":57,"level":0,"type":10,"direction":0},{"id":25057,"x":8,"y":58,"level":0,"type":10,"direction":0},{"id":25057,"x":8,"y":59,"level":0,"type":10,"direction":0},{"id":25057,"x":8,"y":60,"level":0,"type":10,"direction":0},{"id":25057,"x":8,"y":61,"level":0,"type":10,"direction":0},{"id":25057,"x":8,"y":62,"level":0,"type":10,"direction":0},{"id":25057,"x":8,"y":63,"level":0,"type":10,"direction":0},{"id":25057,"x":9,"y":26,"level":0,"type":10,"direction":0},{"id":25057,"x":9,"y":27,"level":0,"type":10,"direction":0},{"id":25057,"x":9,"y":28,"level":0,"type":10,"direction":0},{"id":25057,"x":9,"y":29,"level":0,"type":10,"direction":0},{"id":25057,"x":9,"y":30,"level":0,"type":10,"direction":0},{"id":25057,"x":9,"y":31,"level":0,"type":10,"direction":0},{"id":25057,"x":9,"y":32,"level":0,"type":10,"direction":0},{"id":25057,"x":9,"y":33,"level":0,"type":10,"direction":0},{"id":25057,"x":9,"y":34,"level":0,"type":10,"direction":0},{"id":25057,"x":9,"y":35,"level":0,"type":10,"direction":0},{"id":25057,"x":9,"y":36,"level":0,"type":10,"direction":0},{"id":25057,"x":9,"y":37,"level":0,"type":10,"direction":0},{"id":25057,"x":9,"y":38,"level":0,"type":10,"direction":0},{"id":25057,"x":9,"y":39,"level":0,"type":10,"direction":0},{"id":25057,"x":9,"y":40,"level":0,"type":10,"direction":0},{"id":25057,"x":9,"y":41,"level":0,"type":10,"direction":0},{"id":25057,"x":9,"y":42,"level":0,"type":10,"direction":0},{"id":25057,"x":9,"y":43,"level":0,"type":10,"direction":0},{"id":25057,"x":9,"y":44,"level":0,"type":10,"direction":0},{"id":25057,"x":9,"y":45,"level":0,"type":10,"direction":0},{"id":25057,"x":9,"y":46,"level":0,"type":10,"direction":0},{"id":25057,"x":9,"y":47,"level":0,"type":10,"direction":0},{"id":25057,"x":9,"y":48,"level":0,"type":10,"direction":0},{"id":25057,"x":9,"y":49,"level":0,"type":10,"direction":0},{"id":25057,"x":9,"y":50,"level":0,"type":10,"direction":0},{"id":25057,"x":9,"y":51,"level":0,"type":10,"direction":0},{"id":25057,"x":9,"y":52,"level":0,"type":10,"direction":0},{"id":25057,"x":9,"y":53,"level":0,"type":10,"direction":0},{"id":25057,"x":9,"y":54,"level":0,"type":10,"direction":0},{"id":25057,"x":9,"y":55,"level":0,"type":10,"direction":0},{"id":25057,"x":9,"y":56,"level":0,"type":10,"direction":0},{"id":25057,"x":9,"y":57,"level":0,"type":10,"direction":0},{"id":25057,"x":9,"y":58,"level":0,"type":10,"direction":0},{"id":25057,"x":9,"y":59,"level":0,"type":10,"direction":0},{"id":25057,"x":9,"y":60,"level":0,"type":10,"direction":0},{"id":25057,"x":9,"y":61,"level":0,"type":10,"direction":0},{"id":25057,"x":9,"y":62,"level":0,"type":10,"direction":0},{"id":25057,"x":9,"y":63,"level":0,"type":10,"direction":0},{"id":25057,"x":10,"y":26,"level":0,"type":10,"direction":0},{"id":25057,"x":10,"y":27,"level":0,"type":10,"direction":0},{"id":25057,"x":10,"y":28,"level":0,"type":10,"direction":0},{"id":25057,"x":10,"y":29,"level":0,"type":10,"direction":0},{"id":25057,"x":10,"y":30,"level":0,"type":10,"direction":0},{"id":25057,"x":10,"y":31,"level":0,"type":10,"direction":0},{"id":25057,"x":10,"y":32,"level":0,"type":10,"direction":0},{"id":25057,"x":10,"y":33,"level":0,"type":10,"direction":0},{"id":25057,"x":10,"y":34,"level":0,"type":10,"direction":0},{"id":25057,"x":10,"y":35,"level":0,"type":10,"direction":0},{"id":25057,"x":10,"y":36,"level":0,"type":10,"direction":0},{"id":25057,"x":10,"y":37,"level":0,"type":10,"direction":0},{"id":25057,"x":10,"y":38,"level":0,"type":10,"direction":0},{"id":25057,"x":10,"y":39,"level":0,"type":10,"direction":0},{"id":25057,"x":10,"y":40,"level":0,"type":10,"direction":0},{"id":25057,"x":10,"y":41,"level":0,"type":10,"direction":0},{"id":25057,"x":10,"y":42,"level":0,"type":10,"direction":0},{"id":25057,"x":10,"y":43,"level":0,"type":10,"direction":0},{"id":25057,"x":10,"y":44,"level":0,"type":10,"direction":0},{"id":25057,"x":10,"y":45,"level":0,"type":10,"direction":0},{"id":25057,"x":10,"y":46,"level":0,"type":10,"direction":0},{"id":25057,"x":10,"y":47,"level":0,"type":10,"direction":0},{"id":25057,"x":10,"y":48,"level":0,"type":10,"direction":0},{"id":25057,"x":10,"y":49,"level":0,"type":10,"direction":0},{"id":25057,"x":10,"y":50,"level":0,"type":10,"direction":0},{"id":25057,"x":10,"y":51,"level":0,"type":10,"direction":0},{"id":25057,"x":10,"y":52,"level":0,"type":10,"direction":0},{"id":25057,"x":10,"y":53,"level":0,"type":10,"direction":0},{"id":25057,"x":10,"y":54,"level":0,"type":10,"direction":0},{"id":25057,"x":10,"y":55,"level":0,"type":10,"direction":0},{"id":25057,"x":10,"y":56,"level":0,"type":10,"direction":0},{"id":25057,"x":10,"y":57,"level":0,"type":10,"direction":0},{"id":25057,"x":10,"y":58,"level":0,"type":10,"direction":0},{"id":25057,"x":10,"y":59,"level":0,"type":10,"direction":0},{"id":25057,"x":10,"y":60,"level":0,"type":10,"direction":0},{"id":25057,"x":10,"y":61,"level":0,"type":10,"direction":0},{"id":25057,"x":10,"y":62,"level":0,"type":10,"direction":0},{"id":25057,"x":10,"y":63,"level":0,"type":10,"direction":0},{"id":25057,"x":0,"y":33,"level":1,"type":10,"direction":0},{"id":25057,"x":0,"y":34,"level":1,"type":10,"direction":0},{"id":25057,"x":0,"y":35,"level":1,"type":10,"direction":0},{"id":25057,"x":0,"y":36,"level":1,"type":10,"direction":0},{"id":25057,"x":0,"y":37,"level":1,"type":10,"direction":0},{"id":25057,"x":0,"y":38,"level":1,"type":10,"direction":0},{"id":25057,"x":0,"y":39,"level":1,"type":10,"direction":0},{"id":25057,"x":0,"y":40,"level":1,"type":10,"direction":0},{"id":25057,"x":0,"y":41,"level":1,"type":10,"direction":0},{"id":25057,"x":0,"y":42,"level":1,"type":10,"direction":0},{"id":25057,"x":0,"y":43,"level":1,"type":10,"direction":0},{"id":25057,"x":0,"y":44,"level":1,"type":10,"direction":0},{"id":25057,"x":0,"y":45,"level":1,"type":10,"direction":0},{"id":25057,"x":0,"y":46,"level":1,"type":10,"direction":0},{"id":25057,"x":0,"y":47,"level":1,"type":10,"direction":0},{"id":25057,"x":0,"y":48,"level":1,"type":10,"direction":0},{"id":25057,"x":0,"y":49,"level":1,"type":10,"direction":0},{"id":25057,"x":0,"y":50,"level":1,"type":10,"direction":0},{"id":25057,"x":0,"y":51,"level":1,"type":10,"direction":0},{"id":25057,"x":0,"y":52,"level":1,"type":10,"direction":0},{"id":25057,"x":0,"y":53,"level":1,"type":10,"direction":0},{"id":25057,"x":0,"y":54,"level":1,"type":10,"direction":0},{"id":25057,"x":0,"y":55,"level":1,"type":10,"direction":0},{"id":25057,"x":0,"y":56,"level":1,"type":10,"direction":0},{"id":25057,"x":0,"y":57,"level":1,"type":10,"direction":0},{"id":25057,"x":0,"y":58,"level":1,"type":10,"direction":0},{"id":25057,"x":2,"y":63,"level":1,"type":10,"direction":2},{"id":25057,"x":3,"y":38,"level":1,"type":10,"direction":2},{"id":25057,"x":3,"y":39,"level":1,"type":10,"direction":2},{"id":25057,"x":3,"y":40,"level":1,"type":10,"direction":2},{"id":25057,"x":3,"y":41,"level":1,"type":10,"direction":2},{"id":25057,"x":3,"y":42,"level":1,"type":10,"direction":2},{"id":25057,"x":3,"y":43,"level":1,"type":10,"direction":2},{"id":25057,"x":3,"y":44,"level":1,"type":10,"direction":2},{"id":25057,"x":3,"y":45,"level":1,"type":10,"direction":2},{"id":25057,"x":3,"y":46,"level":1,"type":10,"direction":2},{"id":25057,"x":3,"y":47,"level":1,"type":10,"direction":2},{"id":25057,"x":3,"y":48,"level":1,"type":10,"direction":2},{"id":25057,"x":3,"y":49,"level":1,"type":10,"direction":2},{"id":25057,"x":3,"y":50,"level":1,"type":10,"direction":2},{"id":25057,"x":3,"y":51,"level":1,"type":10,"direction":2},{"id":25057,"x":3,"y":52,"level":1,"type":10,"direction":2},{"id":25057,"x":3,"y":53,"level":1,"type":10,"direction":2},{"id":25057,"x":3,"y":54,"level":1,"type":10,"direction":2},{"id":25057,"x":3,"y":55,"level":1,"type":10,"direction":2},{"id":25057,"x":3,"y":56,"level":1,"type":10,"direction":2},{"id":25057,"x":3,"y":57,"level":1,"type":10,"direction":2},{"id":25057,"x":3,"y":58,"level":1,"type":10,"direction":2},{"id":25057,"x":3,"y":59,"level":1,"type":10,"direction":2},{"id":25057,"x":3,"y":60,"level":1,"type":10,"direction":2},{"id":25057,"x":3,"y":61,"level":1,"type":10,"direction":2},{"id":25057,"x":3,"y":62,"level":1,"type":10,"direction":2},{"id":25057,"x":3,"y":63,"level":1,"type":10,"direction":2},{"id":25057,"x":4,"y":35,"level":1,"type":10,"direction":2},{"id":25057,"x":4,"y":36,"level":1,"type":10,"direction":2},{"id":25057,"x":4,"y":37,"level":1,"type":10,"direction":2},{"id":25057,"x":4,"y":38,"level":1,"type":10,"direction":2},{"id":25057,"x":4,"y":39,"level":1,"type":10,"direction":2},{"id":25057,"x":4,"y":40,"level":1,"type":10,"direction":2},{"id":25057,"x":4,"y":41,"level":1,"type":10,"direction":2},{"id":25057,"x":4,"y":42,"level":1,"type":10,"direction":2},{"id":25057,"x":4,"y":43,"level":1,"type":10,"direction":2},{"id":25057,"x":4,"y":44,"level":1,"type":10,"direction":2},{"id":25057,"x":4,"y":45,"level":1,"type":10,"direction":2},{"id":25057,"x":4,"y":46,"level":1,"type":10,"direction":2},{"id":25057,"x":4,"y":47,"level":1,"type":10,"direction":2},{"id":25057,"x":4,"y":48,"level":1,"type":10,"direction":2},{"id":25057,"x":4,"y":49,"level":1,"type":10,"direction":2},{"id":25057,"x":4,"y":50,"level":1,"type":10,"direction":2},{"id":25057,"x":4,"y":51,"level":1,"type":10,"direction":2},{"id":25057,"x":4,"y":52,"level":1,"type":10,"direction":2},{"id":25057,"x":4,"y":53,"level":1,"type":10,"direction":2},{"id":25057,"x":4,"y":54,"level":1,"type":10,"direction":2},{"id":25057,"x":4,"y":55,"level":1,"type":10,"direction":2},{"id":25057,"x":4,"y":56,"level":1,"type":10,"direction":2},{"id":25057,"x":4,"y":57,"level":1,"type":10,"direction":2},{"id":25057,"x":4,"y":58,"level":1,"type":10,"direction":2},{"id":25057,"x":4,"y":59,"level":1,"type":10,"direction":2},{"id":25057,"x":4,"y":60,"level":1,"type":10,"direction":2},{"id":25057,"x":4,"y":61,"level":1,"type":10,"direction":2},{"id":25057,"x":4,"y":62,"level":1,"type":10,"direction":2},{"id":25057,"x":4,"y":63,"level":1,"type":10,"direction":2},{"id":25057,"x":5,"y":33,"level":1,"type":10,"direction":2},{"id":25057,"x":5,"y":34,"level":1,"type":10,"direction":2},{"id":25057,"x":5,"y":35,"level":1,"type":10,"direction":2},{"id":25057,"x":5,"y":36,"level":1,"type":10,"direction":2},{"id":25057,"x":5,"y":37,"level":1,"type":10,"direction":2},{"id":25057,"x":5,"y":38,"level":1,"type":10,"direction":2},{"id":25057,"x":5,"y":39,"level":1,"type":10,"direction":2},{"id":25057,"x":5,"y":40,"level":1,"type":10,"direction":2},{"id":25057,"x":5,"y":41,"level":1,"type":10,"direction":2},{"id":25057,"x":5,"y":42,"level":1,"type":10,"direction":2},{"id":25057,"x":5,"y":43,"level":1,"type":10,"direction":2},{"id":25057,"x":5,"y":44,"level":1,"type":10,"direction":2},{"id":25057,"x":5,"y":45,"level":1,"type":10,"direction":2},{"id":25057,"x":5,"y":46,"level":1,"type":10,"direction":2},{"id":25057,"x":5,"y":47,"level":1,"type":10,"direction":2},{"id":25057,"x":5,"y":48,"level":1,"type":10,"direction":2},{"id":25057,"x":5,"y":49,"level":1,"type":10,"direction":2},{"id":25057,"x":5,"y":50,"level":1,"type":10,"direction":2},{"id":25057,"x":5,"y":51,"level":1,"type":10,"direction":2},{"id":25057,"x":5,"y":52,"level":1,"type":10,"direction":2},{"id":25057,"x":5,"y":53,"level":1,"type":10,"direction":2},{"id":25057,"x":5,"y":54,"level":1,"type":10,"direction":2},{"id":25057,"x":5,"y":55,"level":1,"type":10,"direction":2},{"id":25057,"x":5,"y":56,"level":1,"type":10,"direction":2},{"id":25057,"x":5,"y":57,"level":1,"type":10,"direction":2},{"id":25057,"x":5,"y":58,"level":1,"type":10,"direction":2},{"id":25057,"x":5,"y":59,"level":1,"type":10,"direction":2},{"id":25057,"x":5,"y":60,"level":1,"type":10,"direction":2},{"id":25057,"x":5,"y":61,"level":1,"type":10,"direction":2},{"id":25057,"x":5,"y":62,"level":1,"type":10,"direction":2},{"id":25057,"x":5,"y":63,"level":1,"type":10,"direction":2},{"id":25057,"x":6,"y":33,"level":1,"type":10,"direction":2},{"id":25057,"x":6,"y":34,"level":1,"type":10,"direction":2},{"id":25057,"x":6,"y":35,"level":1,"type":10,"direction":2},{"id":25057,"x":6,"y":36,"level":1,"type":10,"direction":2},{"id":25057,"x":6,"y":37,"level":1,"type":10,"direction":2},{"id":25057,"x":6,"y":38,"level":1,"type":10,"direction":2},{"id":25057,"x":6,"y":39,"level":1,"type":10,"direction":2},{"id":25057,"x":6,"y":40,"level":1,"type":10,"direction":2},{"id":25057,"x":6,"y":41,"level":1,"type":10,"direction":2},{"id":25057,"x":6,"y":42,"level":1,"type":10,"direction":2},{"id":25057,"x":6,"y":43,"level":1,"type":10,"direction":2},{"id":25057,"x":6,"y":44,"level":1,"type":10,"direction":2},{"id":25057,"x":6,"y":45,"level":1,"type":10,"direction":2},{"id":25057,"x":6,"y":46,"level":1,"type":10,"direction":2},{"id":25057,"x":6,"y":47,"level":1,"type":10,"direction":2},{"id":25057,"x":6,"y":48,"level":1,"type":10,"direction":2},{"id":25057,"x":6,"y":49,"level":1,"type":10,"direction":2},{"id":25057,"x":6,"y":50,"level":1,"type":10,"direction":2},{"id":25057,"x":6,"y":51,"level":1,"type":10,"direction":2},{"id":25057,"x":6,"y":52,"level":1,"type":10,"direction":2},{"id":25057,"x":6,"y":53,"level":1,"type":10,"direction":2},{"id":25057,"x":6,"y":54,"level":1,"type":10,"direction":2},{"id":25057,"x":6,"y":55,"level":1,"type":10,"direction":2},{"id":25057,"x":6,"y":56,"level":1,"type":10,"direction":2},{"id":25057,"x":6,"y":57,"level":1,"type":10,"direction":2},{"id":25057,"x":6,"y":58,"level":1,"type":10,"direction":2},{"id":25057,"x":6,"y":59,"level":1,"type":10,"direction":2},{"id":25057,"x":6,"y":60,"level":1,"type":10,"direction":2},{"id":25057,"x":6,"y":61,"level":1,"type":10,"direction":2},{"id":25057,"x":6,"y":62,"level":1,"type":10,"direction":2},{"id":25057,"x":6,"y":63,"level":1,"type":10,"direction":2},{"id":25057,"x":7,"y":36,"level":1,"type":10,"direction":2},{"id":25057,"x":7,"y":37,"level":1,"type":10,"direction":2},{"id":25057,"x":7,"y":38,"level":1,"type":10,"direction":2},{"id":25057,"x":7,"y":39,"level":1,"type":10,"direction":2},{"id":25057,"x":7,"y":40,"level":1,"type":10,"direction":2},{"id":25057,"x":7,"y":41,"level":1,"type":10,"direction":2},{"id":25057,"x":7,"y":42,"level":1,"type":10,"direction":2},{"id":25057,"x":7,"y":43,"level":1,"type":10,"direction":2},{"id":25057,"x":7,"y":44,"level":1,"type":10,"direction":2},{"id":25057,"x":7,"y":45,"level":1,"type":10,"direction":2},{"id":25057,"x":7,"y":46,"level":1,"type":10,"direction":2},{"id":25057,"x":7,"y":47,"level":1,"type":10,"direction":2},{"id":25057,"x":7,"y":48,"level":1,"type":10,"direction":2},{"id":25057,"x":7,"y":49,"level":1,"type":10,"direction":2},{"id":25057,"x":7,"y":50,"level":1,"type":10,"direction":2},{"id":25057,"x":7,"y":51,"level":1,"type":10,"direction":2},{"id":25057,"x":7,"y":52,"level":1,"type":10,"direction":2},{"id":25057,"x":7,"y":53,"level":1,"type":10,"direction":2},{"id":25057,"x":7,"y":54,"level":1,"type":10,"direction":2},{"id":25057,"x":7,"y":55,"level":1,"type":10,"direction":2},{"id":25057,"x":7,"y":56,"level":1,"type":10,"direction":2},{"id":25057,"x":7,"y":57,"level":1,"type":10,"direction":2},{"id":25057,"x":7,"y":58,"level":1,"type":10,"direction":2},{"id":25057,"x":7,"y":59,"level":1,"type":10,"direction":2},{"id":25057,"x":7,"y":60,"level":1,"type":10,"direction":2},{"id":25057,"x":7,"y":61,"level":1,"type":10,"direction":2},{"id":25057,"x":7,"y":62,"level":1,"type":10,"direction":2},{"id":25057,"x":7,"y":63,"level":1,"type":10,"direction":2},{"id":25057,"x":8,"y":38,"level":1,"type":10,"direction":2},{"id":25057,"x":8,"y":39,"level":1,"type":10,"direction":2},{"id":25057,"x":8,"y":40,"level":1,"type":10,"direction":2},{"id":25057,"x":8,"y":41,"level":1,"type":10,"direction":2},{"id":25057,"x":8,"y":42,"level":1,"type":10,"direction":2},{"id":25057,"x":8,"y":43,"level":1,"type":10,"direction":2},{"id":25057,"x":8,"y":44,"level":1,"type":10,"direction":2},{"id":25057,"x":8,"y":45,"level":1,"type":10,"direction":2},{"id":25057,"x":8,"y":46,"level":1,"type":10,"direction":2},{"id":25057,"x":8,"y":47,"level":1,"type":10,"direction":2},{"id":25057,"x":8,"y":48,"level":1,"type":10,"direction":2},{"id":25057,"x":8,"y":49,"level":1,"type":10,"direction":2},{"id":25057,"x":8,"y":50,"level":1,"type":10,"direction":2},{"id":25057,"x":8,"y":51,"level":1,"type":10,"direction":2},{"id":25057,"x":8,"y":52,"level":1,"type":10,"direction":2},{"id":25057,"x":8,"y":53,"level":1,"type":10,"direction":2},{"id":25057,"x":8,"y":54,"level":1,"type":10,"direction":2},{"id":25057,"x":8,"y":55,"level":1,"type":10,"direction":2},{"id":25057,"x":8,"y":56,"level":1,"type":10,"direction":2},{"id":25057,"x":8,"y":57,"level":1,"type":10,"direction":2},{"id":25057,"x":8,"y":58,"level":1,"type":10,"direction":2},{"id":25057,"x":8,"y":59,"level":1,"type":10,"direction":2},{"id":25057,"x":8,"y":60,"level":1,"type":10,"direction":2},{"id":25057,"x":8,"y":61,"level":1,"type":10,"direction":2},{"id":25057,"x":8,"y":62,"level":1,"type":10,"direction":2},{"id":25057,"x":8,"y":63,"level":1,"type":10,"direction":2},{"id":25057,"x":9,"y":39,"level":1,"type":10,"direction":2},{"id":25057,"x":9,"y":40,"level":1,"type":10,"direction":2},{"id":25057,"x":9,"y":41,"level":1,"type":10,"direction":2},{"id":25057,"x":9,"y":42,"level":1,"type":10,"direction":2},{"id":25057,"x":9,"y":43,"level":1,"type":10,"direction":2},{"id":25057,"x":9,"y":44,"level":1,"type":10,"direction":2},{"id":25057,"x":9,"y":45,"level":1,"type":10,"direction":2},{"id":25057,"x":9,"y":46,"level":1,"type":10,"direction":2},{"id":25057,"x":9,"y":47,"level":1,"type":10,"direction":2},{"id":25057,"x":9,"y":48,"level":1,"type":10,"direction":2},{"id":25057,"x":9,"y":49,"level":1,"type":10,"direction":2},{"id":25057,"x":9,"y":50,"level":1,"type":10,"direction":2},{"id":25057,"x":9,"y":51,"level":1,"type":10,"direction":2},{"id":25057,"x":9,"y":52,"level":1,"type":10,"direction":2},{"id":25057,"x":9,"y":53,"level":1,"type":10,"direction":2},{"id":25057,"x":9,"y":54,"level":1,"type":10,"direction":2},{"id":25057,"x":9,"y":55,"level":1,"type":10,"direction":2},{"id":25057,"x":9,"y":56,"level":1,"type":10,"direction":2},{"id":25057,"x":9,"y":57,"level":1,"type":10,"direction":2},{"id":25057,"x":9,"y":58,"level":1,"type":10,"direction":2},{"id":25057,"x":9,"y":59,"level":1,"type":10,"direction":2},{"id":25057,"x":9,"y":60,"level":1,"type":10,"direction":2},{"id":25057,"x":9,"y":61,"level":1,"type":10,"direction":2},{"id":25057,"x":9,"y":62,"level":1,"type":10,"direction":2},{"id":25057,"x":9,"y":63,"level":1,"type":10,"direction":2},{"id":25057,"x":1,"y":43,"level":2,"type":10,"direction":1},{"id":25057,"x":1,"y":44,"level":2,"type":10,"direction":1},{"id":25057,"x":1,"y":45,"level":2,"type":10,"direction":1},{"id":25057,"x":1,"y":46,"level":2,"type":10,"direction":1},{"id":25057,"x":2,"y":38,"level":2,"type":10,"direction":1},{"id":25057,"x":2,"y":39,"level":2,"type":10,"direction":1},{"id":25057,"x":2,"y":40,"level":2,"type":10,"direction":1},{"id":25057,"x":2,"y":41,"level":2,"type":10,"direction":1},{"id":25057,"x":2,"y":42,"level":2,"type":10,"direction":1},{"id":25057,"x":2,"y":43,"level":2,"type":10,"direction":1},{"id":25057,"x":2,"y":44,"level":2,"type":10,"direction":1},{"id":25057,"x":2,"y":45,"level":2,"type":10,"direction":1},{"id":25057,"x":2,"y":46,"level":2,"type":10,"direction":1},{"id":25057,"x":2,"y":47,"level":2,"type":10,"direction":1},{"id":25057,"x":2,"y":48,"level":2,"type":10,"direction":1},{"id":25057,"x":2,"y":49,"level":2,"type":10,"direction":1},{"id":25057,"x":3,"y":38,"level":2,"type":10,"direction":1},{"id":25057,"x":3,"y":39,"level":2,"type":10,"direction":1},{"id":25057,"x":3,"y":40,"level":2,"type":10,"direction":1},{"id":25057,"x":3,"y":41,"level":2,"type":10,"direction":1},{"id":25057,"x":3,"y":42,"level":2,"type":10,"direction":1},{"id":25057,"x":3,"y":43,"level":2,"type":10,"direction":1},{"id":25057,"x":3,"y":44,"level":2,"type":10,"direction":1},{"id":25057,"x":3,"y":45,"level":2,"type":10,"direction":1},{"id":25057,"x":3,"y":46,"level":2,"type":10,"direction":1},{"id":25057,"x":3,"y":47,"level":2,"type":10,"direction":1},{"id":25057,"x":3,"y":48,"level":2,"type":10,"direction":1},{"id":25057,"x":3,"y":49,"level":2,"type":10,"direction":1},{"id":25057,"x":4,"y":42,"level":2,"type":10,"direction":1},{"id":25057,"x":4,"y":43,"level":2,"type":10,"direction":1},{"id":25057,"x":4,"y":44,"level":2,"type":10,"direction":1},{"id":25057,"x":4,"y":45,"level":2,"type":10,"direction":1},{"id":25057,"x":4,"y":46,"level":2,"type":10,"direction":1},{"id":25057,"x":4,"y":47,"level":2,"type":10,"direction":1},{"id":25057,"x":4,"y":48,"level":2,"type":10,"direction":1},{"id":25057,"x":4,"y":49,"level":2,"type":10,"direction":1},{"id":25057,"x":5,"y":42,"level":2,"type":10,"direction":1},{"id":25057,"x":5,"y":43,"level":2,"type":10,"direction":1},{"id":25057,"x":5,"y":44,"level":2,"type":10,"direction":1},{"id":25057,"x":5,"y":45,"level":2,"type":10,"direction":1},{"id":25057,"x":5,"y":46,"level":2,"type":10,"direction":1},{"id":25057,"x":5,"y":47,"level":2,"type":10,"direction":1},{"id":25057,"x":5,"y":48,"level":2,"type":10,"direction":1},{"id":25057,"x":5,"y":49,"level":2,"type":10,"direction":1},{"id":25057,"x":6,"y":42,"level":2,"type":10,"direction":1},{"id":25057,"x":6,"y":43,"level":2,"type":10,"direction":1},{"id":25057,"x":6,"y":44,"level":2,"type":10,"direction":1},{"id":25057,"x":6,"y":45,"level":2,"type":10,"direction":1},{"id":25057,"x":6,"y":46,"level":2,"type":10,"direction":1},{"id":25057,"x":6,"y":47,"level":2,"type":10,"direction":1},{"id":25057,"x":6,"y":48,"level":2,"type":10,"direction":1},{"id":25057,"x":7,"y":42,"level":2,"type":10,"direction":1},{"id":25057,"x":7,"y":43,"level":2,"type":10,"direction":1},{"id":25057,"x":7,"y":44,"level":2,"type":10,"direction":1}]}